machine_learning/GaltonFamiliesPreprocessing.py
machine_learning/TitanicDatasetPreprocessing.py
machine_learning/__init__.py
machine_learning/data/GaltonFamilies.csv
machine_learning/data/test.csv
machine_learning/data/train.csv
machine_learning/models/Adaboost.py
machine_learning/models/GradientBoosting.py
machine_learning/models/KNearestNeighbours.py
machine_learning/models/LinearRegression.py
machine_learning/models/LogisticRegression.py
machine_learning/models/NaiveBayes.py
machine_learning/models/RandomForest.py
machine_learning/models/RegressionTree.py
machine_learning/models/SVM.py
machine_learning/models/XGBoost.py
machine_learning/models/__init__.py
machine_learning/scores/__init__.py
machine_learning/scores/get_scores.py
machine_learning/scores/nested_cross_validation.py
machine_learning/src/__init__.py
machine_learning/src/Adaboost/AdaboostModel.py
machine_learning/src/Adaboost/Stump.py
machine_learning/src/Adaboost/__init__.py
machine_learning/src/ExtremeGradientBoost/XGBoostModel.py
machine_learning/src/ExtremeGradientBoost/XGboostTree.py
machine_learning/src/ExtremeGradientBoost/__init__.py
machine_learning/src/GradientBoosting/GradientBoostingModel.py
machine_learning/src/GradientBoosting/Tree.py
machine_learning/src/GradientBoosting/__init__.py
machine_learning/src/KNearestNeighbours/KNearestNeighboursModel.py
machine_learning/src/KNearestNeighbours/__init__.py
machine_learning/src/LinearRegression/LinearRegressionModel.py
machine_learning/src/LinearRegression/__init__.py
machine_learning/src/LogisticRegression/LogisticRegressionModel.py
machine_learning/src/LogisticRegression/__init__.py
machine_learning/src/NaiveBayes/GaussianNaiveBayes.py
machine_learning/src/NaiveBayes/MultinomialNaiveBayes.py
machine_learning/src/NaiveBayes/NaiveBayesModel.py
machine_learning/src/NaiveBayes/__init__.py
machine_learning/src/RandomForest/RandomForestModel.py
machine_learning/src/RandomForest/Tree.py
machine_learning/src/RandomForest/__init__.py
machine_learning_models-0.0.2.dist-info/LICENSE
machine_learning_models-0.0.2.dist-info/METADATA
machine_learning_models-0.0.2.dist-info/WHEEL
machine_learning_models-0.0.2.dist-info/top_level.txt
machine_learning_models-0.0.2.dist-info/RECORD
