Metadata-Version: 2.1
Name: machine_learning_models
Version: 0.0.2
Summary: Implementations of most popular machine learning algorithms
Home-page: https://github.com/mgrzanka/MachineLearning.git
Author: Małgorzata Grzanka
Author-email: mgrzanka45@gmail.com
Classifier: Programming Language :: Python :: 3
Classifier: License :: OSI Approved :: MIT License
Classifier: Operating System :: OS Independent
Requires-Python: >=3.11.2
License-File: LICENSE
